django_psutil_dash/__init__.py
django_psutil_dash/apps.py
django_psutil_dash/static/psutildash/css/tabler.min.css
django_psutil_dash/static/psutildash/js/tabler.min.js
django_psutil_dash/stats.py
django_psutil_dash/templates/psutildash/base.html
django_psutil_dash/templates/psutildash/dashboard.html
django_psutil_dash/templates/psutildash/disks.html
django_psutil_dash/templates/psutildash/layout.html
django_psutil_dash/templates/psutildash/network.html
django_psutil_dash/templates/psutildash/processes.html
django_psutil_dash/urls.py
django_psutil_dash/views.py
django_psutil_dash-0.1.3.dist-info/LICENSE
django_psutil_dash-0.1.3.dist-info/METADATA
django_psutil_dash-0.1.3.dist-info/WHEEL
django_psutil_dash-0.1.3.dist-info/RECORD
