Metadata-Version: 2.1
Name: django-psutil-dash
Version: 0.1.3
Summary: 
License: MIT
Author: tsarbas
Requires-Python: >=3.10,<4.0
Classifier: License :: OSI Approved :: MIT License
Classifier: Programming Language :: Python :: 3
Classifier: Programming Language :: Python :: 3.10
Classifier: Programming Language :: Python :: 3.11
Classifier: Programming Language :: Python :: 3.12
Requires-Dist: humanize (>=4.9.0,<5.0.0)
Requires-Dist: psutil (>=5.9.8,<6.0.0)
